pokepoke_miss/__init__.py
pokepoke_miss/__main__.py
pokepoke_miss-0.1.20.dist-info/LICENSE
pokepoke_miss-0.1.20.dist-info/METADATA
pokepoke_miss-0.1.20.dist-info/WHEEL
pokepoke_miss-0.1.20.dist-info/RECORD
