Metadata-Version: 2.1
Name: pokepoke_miss
Version: 0.1.20
Summary: wmc的戳一戳回复插件，消息内容、概率都可以定制喔~
Home-page: https://github.com/shengwang52005/pokepoke_miss
License: MIT
Author: Miaowing
Author-email: shengwang52005@163.com
Requires-Python: >=3.10,<4.0
Classifier: License :: OSI Approved :: MIT License
Classifier: Programming Language :: Python :: 3
Classifier: Programming Language :: Python :: 3.10
Classifier: Programming Language :: Python :: 3.11
Classifier: Programming Language :: Python :: 3.12
Requires-Dist: httpx (>=0.27.0)
Requires-Dist: nonebot-adapter-onebot (>=2.3.1)
Requires-Dist: nonebot2 (>=2.3.2)
Requires-Dist: pil_utils (==0.1.10)
Project-URL: Repository, https://github.com/shengwang52005/pokepoke_miss
